let_me_google_that/let_me_google_that/__init__.py
let_me_google_that/README.rst
let_me_google_that/tests/__init__.py
let_me_google_that/tests/test_let_me_google_that.py
let_me_google_that-0.0.4.dist-info/WHEEL
let_me_google_that-0.0.4.dist-info/METADATA
let_me_google_that-0.0.4.dist-info/RECORD
